Metadata-Version: 1.0
Name: xsun-probability
Version: 0.1
Summary: Gaussian and Binomial distributions
Home-page: UNKNOWN
Author: Xiake Sun
Author-email: xiakesun0711@gmail.com
License: UNKNOWN
Platform: UNKNOWN
